.gitattributes
.gitignore
README.md
setup.cfg
setup.py
dartmouth_banner.egg-info/PKG-INFO
dartmouth_banner.egg-info/SOURCES.txt
dartmouth_banner.egg-info/dependency_links.txt
dartmouth_banner.egg-info/requires.txt
dartmouth_banner.egg-info/top_level.txt
src/dartmouth_banner.py