Metadata-Version: 1.1
Name: dartmouth-banner
Version: 1.0.0
Summary: Python API for interacting with Dartmouth Banner
Home-page: https://github.com/dado3212/dartmouth_banner
Author: Alex Beals
Author-email: Alex.Beals.18@dartmouth.edu
License: BSD
Keywords: api dartmouth banner
Platform: UNKNOWN
Classifier: Development Status :: 3 - Alpha
Classifier: Intended Audience :: Developers
Classifier: Programming Language :: Python :: 2.6
Classifier: Programming Language :: Python :: 2.7
Classifier: Programming Language :: Python :: 3
Classifier: Programming Language :: Python :: 3.2
Classifier: Programming Language :: Python :: 3.3
Classifier: Programming Language :: Python :: 3.4
